<?xml version="1.0" encoding="UTF-8"?>
<world width="30" height="30">
  <cell x="10" y="7"/>
  <cell x="11" y="7"/>
  <cell x="17" y="7"/>
  <cell x="18" y="7"/>
  <cell x="11" y="8"/>
  <cell x="12" y="8"/>
  <cell x="16" y="8"/>
  <cell x="17" y="8"/>
  <cell x="8" y="9"/>
  <cell x="11" y="9"/>
  <cell x="13" y="9"/>
  <cell x="15" y="9"/>
  <cell x="17" y="9"/>
  <cell x="20" y="9"/>
  <cell x="8" y="10"/>
  <cell x="9" y="10"/>
  <cell x="10" y="10"/>
  <cell x="12" y="10"/>
  <cell x="13" y="10"/>
  <cell x="15" y="10"/>
  <cell x="16" y="10"/>
  <cell x="18" y="10"/>
  <cell x="19" y="10"/>
  <cell x="20" y="10"/>
  <cell x="9" y="11"/>
  <cell x="11" y="11"/>
  <cell x="13" y="11"/>
  <cell x="15" y="11"/>
  <cell x="17" y="11"/>
  <cell x="19" y="11"/>
  <cell x="10" y="12"/>
  <cell x="11" y="12"/>
  <cell x="12" y="12"/>
  <cell x="16" y="12"/>
  <cell x="17" y="12"/>
  <cell x="18" y="12"/>
  <cell x="10" y="14"/>
  <cell x="11" y="14"/>
  <cell x="12" y="14"/>
  <cell x="16" y="14"/>
  <cell x="17" y="14"/>
  <cell x="18" y="14"/>
  <cell x="9" y="15"/>
  <cell x="11" y="15"/>
  <cell x="13" y="15"/>
  <cell x="15" y="15"/>
  <cell x="17" y="15"/>
  <cell x="19" y="15"/>
  <cell x="8" y="16"/>
  <cell x="9" y="16"/>
  <cell x="10" y="16"/>
  <cell x="12" y="16"/>
  <cell x="13" y="16"/>
  <cell x="15" y="16"/>
  <cell x="16" y="16"/>
  <cell x="18" y="16"/>
  <cell x="19" y="16"/>
  <cell x="20" y="16"/>
  <cell x="8" y="17"/>
  <cell x="11" y="17"/>
  <cell x="13" y="17"/>
  <cell x="15" y="17"/>
  <cell x="17" y="17"/>
  <cell x="20" y="17"/>
  <cell x="11" y="18"/>
  <cell x="12" y="18"/>
  <cell x="16" y="18"/>
  <cell x="17" y="18"/>
  <cell x="10" y="19"/>
  <cell x="11" y="19"/>
  <cell x="17" y="19"/>
  <cell x="18" y="19"/>
</world>
